{"0": "NON_adhesion_ar", "1": "NON_adhesion_employeur_ar", "2": "NON_adhesion_employeur_fr", "3": "NON_adhesion_fr", "4": "OUI_adhesion_ar", "5": "OUI_adhesion_employeur_ar", "6": "OUI_adhesion_employeur_fr", "7": "OUI_adhesion_fr", "8": "adhesion_ar", "9": "adhesion_employeur_ar", "10": "adhesion_employeur_fr", "11": "adhesion_fr", "12": "affirmation_ar", "13": "affirmation_fr", "14": "ask_help_ar", "15": "ask_help_employeur_ar", "16": "ask_help_employeur_fr", "17": "ask_help_fr", "18": "ask_language", "19": "avantages_retraite_ar", "20": "avantages_retraite_fr", "21": "cnss_ar", "22": "cnss_fr", "23": "cotisation_ar", "24": "cotisation_employeur_ar", "25": "cotisation_employeur_fr", "26": "cotisation_fr", "27": "deny_ar", "28": "deny_fr", "29": "employeur_ar", "30": "employeur_fr", "31": "employ\u00e9_ar", "32": "employ\u00e9_fr", "33": "goodbye_ar", "34": "goodbye_fr", "35": "greet_ar", "36": "greet_fr", "37": "language_ar", "38": "language_fr", "39": "retraite_ar", "40": "retraite_fr", "41": "thanks_ar", "42": "thanks_fr"}